pytextree/__init__.py
pytextree/node.py
pytextree/tex_walker.py
pytextree-0.1.1.dist-info/LICENSE
pytextree-0.1.1.dist-info/METADATA
pytextree-0.1.1.dist-info/WHEEL
pytextree-0.1.1.dist-info/top_level.txt
pytextree-0.1.1.dist-info/RECORD
