Metadata-Version: 2.1
Name: pytextree
Version: 0.1.1
Summary: Create a tree object from a LaTeX project
Home-page: https://github.com/PebbleBonk/pytextree
Author: Olli Riikonen
Author-email: pebblebonk@gmail.com
License: MIT
Platform: UNKNOWN
Classifier: License :: OSI Approved :: MIT License
Classifier: Programming Language :: Python :: 3
Classifier: Programming Language :: Python :: 3.7
Requires-Python: >=3.7.0
Requires-Dist: anytree (==2.8.0)
Requires-Dist: numpy (==1.18.2)
Requires-Dist: six (==1.14.0)
